{"settings":{"opExample":[],"licence":"none","isPublic":false},"ops":[{"opId":"b0472a1d-db16-4ba6-8787-f300fbdc77bb","objName":"Ops.Gl.MainLoop","id":"38dfbdfe-c4c2-47ba-88ac-ebfcf59b270a","uiAttribs":{"history":{"createdAt":1643894840556,"createdBy":{"name":"b2renger"},"lastInteractionAt":1643894840556,"lastInteractionBy":{"name":"b2renger"}},"subPatch":0,"translate":{"x":-168,"y":-200},"selected":false},"portsIn":[{"name":"FPS Limit","value":0},{"name":"Reduce FPS not focussed","value":true},{"name":"Reduce FPS loading","value":0},{"name":"Clear","value":true},{"name":"ClearAlpha","value":true},{"name":"Fullscreen Button","value":false},{"name":"Active","value":true},{"name":"Hires Displays","value":false}],"portsOut":[{"name":"trigger","links":[{"portIn":"Render","portOut":"trigger","objIn":"4dbb0cad-5575-46e9-ba48-c5258e0c42e9","objOut":"38dfbdfe-c4c2-47ba-88ac-ebfcf59b270a"}]},{"name":"width","value":640},{"name":"height","value":360}]},{"opId":"37b92ba4-cea5-42ae-bf28-a513ca28549c","objName":"Ops.Gl.Meshes.Cube_v2","id":"eb0165b1-412d-4dd9-8b9c-af38f01244c2","uiAttribs":{"history":{"createdAt":1643894857026,"createdBy":{"name":"b2renger"},"lastInteractionAt":1643894857026,"lastInteractionBy":{"name":"b2renger"}},"subPatch":0,"translate":{"x":-228,"y":220},"selected":false},"portsIn":[{"name":"Render"},{"name":"Render Mesh","value":true},{"name":"Width","value":1},{"name":"Length","value":1},{"name":"Height","value":1},{"name":"Center","value":true},{"name":"Mapping index","value":0},{"name":"Mapping","value":"Side"},{"name":"Bias","value":0},{"name":"Flip X","value":true},{"name":"Top","value":true},{"name":"Bottom","value":true},{"name":"Left","value":true},{"name":"Right","value":true},{"name":"Front","value":true},{"name":"Back","value":true}],"portsOut":[{"name":"Next","value":0},{"name":"geometry"}]},{"opId":"c1dd6e76-61b4-471a-b8d1-f550a5a9a4f4","objName":"Ops.Gl.Shader.MatCapMaterialNew_v3","id":"4dbb0cad-5575-46e9-ba48-c5258e0c42e9","uiAttribs":{"history":{"createdAt":1643894867801,"createdBy":{"name":"b2renger"},"lastInteractionAt":1643894867801,"lastInteractionBy":{"name":"b2renger"}},"subPatch":0,"translate":{"x":-228,"y":0},"selected":false},"portsIn":[{"name":"Render"},{"name":"MatCap","value":0},{"name":"Diffuse","value":0},{"name":"Normal","value":0},{"name":"Specular Mask","value":0},{"name":"Specular MatCap","value":0},{"name":"AO Texture","value":0},{"name":"Opacity Texture","value":0},{"name":"r","value":1},{"name":"g","value":1},{"name":"b","value":1},{"name":"Opacity","value":1},{"name":"AO Intensity","value":1},{"name":"Normal Map Intensity","value":1},{"name":"Repeat X","value":1},{"name":"Repeat Y","value":1},{"name":"Offset X","value":0},{"name":"Offset Y","value":0},{"name":"Screen Space Normals","value":0},{"name":"Calc normal tangents","value":true},{"name":"Opacity TexCoords Transform","value":false},{"name":"Discard Transparent Pixels","value":0},{"name":"Alpha Mask Source index","value":0},{"name":"Alpha Mask Source","value":"Luminance"}],"portsOut":[{"name":"Next","links":[{"portIn":"render","portOut":"Next","objIn":"2dfc490d-590e-424d-9086-d70ade1a2784","objOut":"4dbb0cad-5575-46e9-ba48-c5258e0c42e9"}]},{"name":"Shader"}]},{"opId":"aac7f721-208f-411a-adb3-79adae2e471a","objName":"Ops.Anim.Timer_v2","id":"85511f23-ab8e-4dc1-abca-47e37b170295","uiAttribs":{"history":{"createdAt":1643894880446,"createdBy":{"name":"b2renger"},"lastInteractionAt":1643894910590,"lastInteractionBy":{"name":"b2renger"}},"subPatch":0,"translate":{"x":-24,"y":60},"selected":false},"portsIn":[{"name":"Speed","value":17.51},{"name":"Play","value":true},{"name":"Reset","value":0},{"name":"Sync to timeline","value":false}],"portsOut":[{"name":"Time","links":[{"portIn":"rotX","portOut":"Time","objIn":"2dfc490d-590e-424d-9086-d70ade1a2784","objOut":"85511f23-ab8e-4dc1-abca-47e37b170295"}]}]},{"opId":"650baeb1-db2d-4781-9af6-ab4e9d4277be","objName":"Ops.Gl.Matrix.Transform","id":"2dfc490d-590e-424d-9086-d70ade1a2784","uiAttribs":{"history":{"createdAt":1643894898193,"createdBy":{"name":"b2renger"},"lastInteractionAt":1643894898193,"lastInteractionBy":{"name":"b2renger"}},"subPatch":0,"translate":{"x":-228,"y":140},"selected":false},"portsIn":[{"name":"render"},{"name":"posX","value":0},{"name":"posY","value":0},{"name":"posZ","value":0},{"name":"scale","value":1},{"name":"rotX"},{"name":"rotY"},{"name":"rotZ"}],"portsOut":[{"name":"trigger","links":[{"portIn":"Render","portOut":"trigger","objIn":"eb0165b1-412d-4dd9-8b9c-af38f01244c2","objOut":"2dfc490d-590e-424d-9086-d70ade1a2784"}]}]},{"opId":"aac7f721-208f-411a-adb3-79adae2e471a","objName":"Ops.Anim.Timer_v2","id":"0e8b96fd-8574-4202-ae48-3f61a68a1332","uiAttribs":{"history":{"createdAt":1643894880446,"createdBy":{"name":"b2renger"},"lastInteractionAt":1643894925206,"lastInteractionBy":{"name":"b2renger"}},"subPatch":0,"translate":{"x":36,"y":100},"selected":false},"portsIn":[{"name":"Speed","value":28.2},{"name":"Play","value":true},{"name":"Reset","value":0},{"name":"Sync to timeline","value":false}],"portsOut":[{"name":"Time","links":[{"portIn":"rotY","portOut":"Time","objIn":"2dfc490d-590e-424d-9086-d70ade1a2784","objOut":"0e8b96fd-8574-4202-ae48-3f61a68a1332"}]}]},{"opId":"aac7f721-208f-411a-adb3-79adae2e471a","objName":"Ops.Anim.Timer_v2","id":"b1ec63f4-d2a0-4530-861b-d418bc64bbd2","uiAttribs":{"history":{"createdAt":1643894880446,"createdBy":{"name":"b2renger"},"lastInteractionAt":1643894938339,"lastInteractionBy":{"name":"b2renger"}},"subPatch":0,"translate":{"x":48,"y":160},"selected":false},"portsIn":[{"name":"Speed","value":26.46},{"name":"Play","value":true},{"name":"Reset","value":0},{"name":"Sync to timeline","value":false}],"portsOut":[{"name":"Time","links":[{"portIn":"rotZ","portOut":"Time","objIn":"2dfc490d-590e-424d-9086-d70ade1a2784","objOut":"b1ec63f4-d2a0-4530-861b-d418bc64bbd2"}]}]}],"users":[],"userOps":[],"tags":[],"_id":"61fbd832d1709c0f569eb216","name":"rotating_cube","userId":"5bec0f9e280355509b0fe50d","created":"2022-02-03T13:27:14.094Z","updated":"2022-02-03T13:29:25.113Z","log":[],"__v":1,"shortId":"Ch8N-W","description":"","buildInfo":{"ui":{"timestamp":1642093519649,"created":"2022-01-13T17:05:19.649Z","git":{"branch":"master","commit":"4915a0a526ca85fa926ed6750446328f8fc1e649","date":"2021-11-30T10:48:51.000Z","message":"icons"}},"host":"cables.gl"},"opsHash":"4be559fa4da22b8f2f8fd36ed99bc3870bde2b59","ui":{"timeLineLength":20,"bookmarks":[],"viewBoxesGl":{"0":{"x":0,"y":0,"z":400}},"renderer":{"w":640,"h":360,"s":1}},"updatedByUser":"b2renger","exports":1}